  {
    "list": [
    { "name": "【R織】" },
    { "name": "【穆昕織】" },
    { "name": "【fei_wu台主】" },
    { "name": "【邱禧瑯】" },
    { "name": "【林俞陌】" },
    { "name": "【顏研】" },
    { "name": "【楊千囍】" },
    { "name": "【古斯達】" },
    { "name": "【權嘉】" },
    { "name": "【李昕】" },
    { "name": "【紅鞋小女孩】" }
   ],
  "listMale": [
    { "name": "【黑狼】" },
    { "name": "【霍爾】" },
    { "name": "【王帝】" },
    { "name": "【張衝蹦】" },
    { "name": "【葉大同】" },
    { "name": "【賴惠洛】" },
    { "name": "【陳建庭】" },
    { "name": "【陳正浩】" },
    { "name": "【武木】" },
    { "name": "【杜斯.....(燒餅)】" },
    { "name": "【金典獄長(經典?】" }
    ],
  "BotResult": [
    { "name": "上漲"  },
    { "name": "下跌" },
    { "name": "疑似被人為炒作無法預測"  },
    { "name": "咕嚕咕嚕..海了" },
    { "name": "雲霄飛車式大起大落~海公主關心您 請備好胃藥" },
    { "name": "燒惹燒惹都貼牆壁了" },
    { "name": "大神相助 股票起飛了" }
    ],
  "sausageCP": [
    { "name": "【尚諦】"  },
    { "name": "連四の【夏威夷披薩鳳梨加量】" },
    { "name": "【大姊香腸】"  },
    { "name": "【這個位置要留給你歐】"  }
    ],
  "profile": {
    "name": "typicode"
  }
}
